karaokemanager/__init__.py
karaokemanager/__main__.py
karaokemanager/commands.py
karaokemanager/config.py
karaokemanager/display_functions.py
karaokemanager/error.py
karaokemanager/exemptions.py
karaokemanager/file_pattern.py
karaokemanager/karaoke_file.py
karaokemanager/karaoke_manager.py
karaokemanager/library.py
karaokemanager/music_file.py
karaokemanager/singer.py
karaokemanager/singer_column.py
karaokemanager/song.py
karaokemanager/song_list.py
karaokemanager/song_selector.py
karaokemanager/state.py
karaokemanager/suggestion_generator.py
karaokemanager-1.0.8.dist-info/METADATA
karaokemanager-1.0.8.dist-info/WHEEL
karaokemanager-1.0.8.dist-info/entry_points.txt
karaokemanager-1.0.8.dist-info/top_level.txt
karaokemanager-1.0.8.dist-info/RECORD
