Metadata-Version: 2.1
Name: karaokemanager
Version: 1.0.8
Summary: Karaoke session management utility
Home-page: https://github.com/peeveen/karaokemanager
Download-URL: https://pypi.org/project/karaokemanager/
Author: Steven Frew
Author-email: steven.fullhouse@gmail.com
License: MIT
Keywords: karaokemanager,karaoke
Requires-Dist: colorama
Requires-Dist: pyyaml
Requires-Dist: textdistance
